streamlit_slb_cognite3dviewer/__init__.py
streamlit_slb_cognite3dviewer/example.py
streamlit_slb_cognite3dviewer/frontend/build/asset-manifest.json
streamlit_slb_cognite3dviewer/frontend/build/favicon.ico
streamlit_slb_cognite3dviewer/frontend/build/index.html
streamlit_slb_cognite3dviewer/frontend/build/logo192.png
streamlit_slb_cognite3dviewer/frontend/build/logo512.png
streamlit_slb_cognite3dviewer/frontend/build/manifest.json
streamlit_slb_cognite3dviewer/frontend/build/robots.txt
streamlit_slb_cognite3dviewer/frontend/build/models/cctv.glb
streamlit_slb_cognite3dviewer/frontend/build/static/css/main.4efb37a3.css
streamlit_slb_cognite3dviewer/frontend/build/static/js/206.4d185342.chunk.js
streamlit_slb_cognite3dviewer/frontend/build/static/js/main.d5f58849.js
streamlit_slb_cognite3dviewer/frontend/build/static/js/main.d5f58849.js.LICENSE.txt
streamlit_slb_cognite3dviewer/frontend/public/favicon.ico
streamlit_slb_cognite3dviewer/frontend/public/index.html
streamlit_slb_cognite3dviewer/frontend/public/logo192.png
streamlit_slb_cognite3dviewer/frontend/public/logo512.png
streamlit_slb_cognite3dviewer/frontend/public/manifest.json
streamlit_slb_cognite3dviewer/frontend/public/robots.txt
streamlit_slb_cognite3dviewer/frontend/public/models/cctv.glb
streamlit_slb_cognite3dviewer/models/__init__.py
streamlit_slb_cognite3dviewer/models/beacon.py
streamlit_slb_cognite3dviewer/models/camera.py
streamlit_slb_cognite3dviewer/models/coordinate.py
streamlit_slb_cognite3dviewer/models/deck.py
streamlit_slb_cognite3dviewer/models/viewer_data.py
streamlit_slb_cognite3dviewer-1.2.3.dist-info/LICENSE
streamlit_slb_cognite3dviewer-1.2.3.dist-info/METADATA
streamlit_slb_cognite3dviewer-1.2.3.dist-info/WHEEL
streamlit_slb_cognite3dviewer-1.2.3.dist-info/top_level.txt
streamlit_slb_cognite3dviewer-1.2.3.dist-info/RECORD
